polytex/__about__.py
polytex/__dataset__.py
polytex/__init__.py
polytex/io.py
polytex/misc.py
polytex/textile.py
polytex/tow.py
polytex/geometry/__entity__.py
polytex/geometry/__init__.py
polytex/geometry/basic.py
polytex/geometry/geometry.py
polytex/geometry/transform.py
polytex/kriging/__init__.py
polytex/kriging/curve2D.py
polytex/kriging/intersect.py
polytex/kriging/mdKrig.py
polytex/kriging/paraSurface.py
polytex/kriging/projection.py
polytex/kriging/tool.py
polytex/kriging/volumeKrig.py
polytex/mesh/__init__.py
polytex/mesh/decimation.py
polytex/mesh/features.py
polytex/mesh/from_image.py
polytex/mesh/mesh.py
polytex/plot/__init__.py
polytex/plot/color_cluster.py
polytex/plot/image_plot.py
polytex/stats/__init__.py
polytex/stats/bw_opt.py
polytex/stats/correlation.py
polytex/stats/kde.py
polytex/thirdparty/__init__.py
polytex/thirdparty/bcolors.py
polytex/thirdparty/loop_stopper.py
polytex/thirdparty/surf2stl/__init__.py
polytex/thirdparty/surf2stl/surf2stl.py
polytex-0.4.5.dist-info/LICENSE.rst
polytex-0.4.5.dist-info/METADATA
polytex-0.4.5.dist-info/WHEEL
polytex-0.4.5.dist-info/top_level.txt
polytex-0.4.5.dist-info/RECORD
