Metadata-Version: 2.1
Name: polytex
Version: 0.4.5
Summary: PolyTex is an open-source toolkit for geometry modeling of fiber tow-based textiles based on volumetric images.
Home-page: https://github.com/binyang424/polytex
Author: Bin Yang
Author-email: bin.yang@polymtl.ca
License: UNKNOWN
Platform: UNKNOWN
Classifier: Development Status :: 2 - Pre-Alpha
Classifier: Intended Audience :: Science/Research
Classifier: License :: OSI Approved :: GNU General Public License (GPL)
Classifier: Operating System :: POSIX :: Linux
Classifier: Programming Language :: Python :: 3.5
Classifier: Programming Language :: Python :: 3.7
Classifier: Programming Language :: Python :: 3.8
Classifier: Programming Language :: Python :: 3.9
Classifier: Programming Language :: Python :: 3.10
Classifier: Programming Language :: Python :: 3.11
Classifier: Programming Language :: Python :: 3.12
License-File: LICENSE.rst
Requires-Dist: numpy ==1.23
Requires-Dist: pyvista ==0.39
Requires-Dist: pandas
Requires-Dist: matplotlib
Requires-Dist: sympy
Requires-Dist: tk
Requires-Dist: shapely
Requires-Dist: SciencePlots
Requires-Dist: opencv-python
Requires-Dist: meshio
Requires-Dist: scikit-learn
Requires-Dist: tqdm
